mcp_get_weather/__init__.py
mcp_get_weather/__main__.py
mcp_get_weather/server.py
mcp_get_weather_20250618-0.1.2.dist-info/METADATA
mcp_get_weather_20250618-0.1.2.dist-info/WHEEL
mcp_get_weather_20250618-0.1.2.dist-info/entry_points.txt
mcp_get_weather_20250618-0.1.2.dist-info/top_level.txt
mcp_get_weather_20250618-0.1.2.dist-info/RECORD
