Metadata-Version: 2.4
Name: mcp-get-weather-20250618
Version: 0.1.2
Summary: 输入OpenWeather-API-KEY，获取天气信息。
Requires-Python: >=3.10
Requires-Dist: build>=1.2.2.post1
Requires-Dist: httpx>=0.28.1
Requires-Dist: mcp>=1.9.4
Requires-Dist: twine>=6.1.0
